{
  "source": "RBA 4pm",
  "source_url": "https://www.rba.gov.au/rss/rss-cb-exchange-rates.xml",
  "as_at_aest": "2026-04-30T16:35:00+10:00",
  "date": "2026-04-30",
  "base": "AUD",
  "rates": [
    {
      "code": "CAD",
      "per_aud": 0.9736,
      "aud_per_unit": 1.0271158586688578,
      "decimals": 4,
      "title": "AU: 0.9736 CAD = 1 AUD 2026-04-30 RBA 4.00 pm Eastern Australian time"
    },
    {
      "code": "CHF",
      "per_aud": 0.5633,
      "aud_per_unit": 1.7752529735487306,
      "decimals": 4,
      "title": "AU: 0.5633 CHF = 1 AUD 2026-04-30 RBA 4.00 pm Eastern Australian time"
    },
    {
      "code": "CNY",
      "per_aud": 4.8663,
      "aud_per_unit": 0.20549493454986334,
      "decimals": 4,
      "title": "AU: 4.8663 CNY = 1 AUD 2026-04-30 RBA 4.00 pm Eastern Australian time"
    },
    {
      "code": "EUR",
      "per_aud": 0.61,
      "aud_per_unit": 1.639344262295082,
      "decimals": 4,
      "title": "AU: 0.6100 EUR = 1 AUD 2026-04-30 RBA 4.00 pm Eastern Australian time"
    },
    {
      "code": "GBP",
      "per_aud": 0.5285,
      "aud_per_unit": 1.892147587511826,
      "decimals": 4,
      "title": "AU: 0.5285 GBP = 1 AUD 2026-04-30 RBA 4.00 pm Eastern Australian time"
    },
    {
      "code": "HKD",
      "per_aud": 5.5734,
      "aud_per_unit": 0.1794236911041734,
      "decimals": 4,
      "title": "AU: 5.5734 HKD = 1 AUD 2026-04-30 RBA 4.00 pm Eastern Australian time"
    },
    {
      "code": "IDR",
      "per_aud": 12361.0,
      "aud_per_unit": 8.08996035919424e-05,
      "decimals": 0,
      "title": "AU: 12361 IDR = 1 AUD 2026-04-30 RBA 4.00 pm Eastern Australian time"
    },
    {
      "code": "INR",
      "per_aud": 67.76,
      "aud_per_unit": 0.014757969303423848,
      "decimals": 2,
      "title": "AU: 67.76 INR = 1 AUD 2026-04-30 RBA 4.00 pm Eastern Australian time"
    },
    {
      "code": "JPY",
      "per_aud": 114.28,
      "aud_per_unit": 0.008750437521876094,
      "decimals": 2,
      "title": "AU: 114.28 JPY = 1 AUD 2026-04-30 RBA 4.00 pm Eastern Australian time"
    },
    {
      "code": "KRW",
      "per_aud": 1054.79,
      "aud_per_unit": 0.0009480560111491388,
      "decimals": 2,
      "title": "AU: 1054.79 KRW = 1 AUD 2026-04-30 RBA 4.00 pm Eastern Australian time"
    },
    {
      "code": "MYR",
      "per_aud": 2.8253,
      "aud_per_unit": 0.35394471383569887,
      "decimals": 4,
      "title": "AU: 2.8253 MYR = 1 AUD 2026-04-30 RBA 4.00 pm Eastern Australian time"
    },
    {
      "code": "NZD",
      "per_aud": 1.2211,
      "aud_per_unit": 0.8189337482597657,
      "decimals": 4,
      "title": "AU: 1.2211 NZD = 1 AUD 2026-04-30 RBA 4.00 pm Eastern Australian time"
    },
    {
      "code": "PGK",
      "per_aud": 3.0872,
      "aud_per_unit": 0.32391811350090693,
      "decimals": 4,
      "title": "AU: 3.0872 PGK = 1 AUD 2026-04-30 RBA 4.00 pm Eastern Australian time"
    },
    {
      "code": "PHP",
      "per_aud": 43.81,
      "aud_per_unit": 0.022825838849577722,
      "decimals": 2,
      "title": "AU: 43.81 PHP = 1 AUD 2026-04-30 RBA 4.00 pm Eastern Australian time"
    },
    {
      "code": "SGD",
      "per_aud": 0.912,
      "aud_per_unit": 1.0964912280701753,
      "decimals": 4,
      "title": "AU: 0.9120 SGD = 1 AUD 2026-04-30 RBA 4.00 pm Eastern Australian time"
    },
    {
      "code": "THB",
      "per_aud": 23.36,
      "aud_per_unit": 0.04280821917808219,
      "decimals": 2,
      "title": "AU: 23.36 THB = 1 AUD 2026-04-30 RBA 4.00 pm Eastern Australian time"
    },
    {
      "code": "TWD",
      "per_aud": 22.56,
      "aud_per_unit": 0.044326241134751775,
      "decimals": 2,
      "title": "AU: 22.56 TWD = 1 AUD 2026-04-30 RBA 4.00 pm Eastern Australian time"
    },
    {
      "code": "USD",
      "per_aud": 0.7113,
      "aud_per_unit": 1.4058765640376774,
      "decimals": 4,
      "title": "AU: 0.7113 USD = 1 AUD 2026-04-30 RBA 4.00 pm Eastern Australian time"
    },
    {
      "code": "VND",
      "per_aud": 18742.0,
      "aud_per_unit": 5.3356098602070216e-05,
      "decimals": 0,
      "title": "AU: 18742 VND = 1 AUD 2026-04-30 RBA 4.00 pm Eastern Australian time"
    },
    {
      "code": "XDR",
      "per_aud": 0.5192,
      "aud_per_unit": 1.926040061633282,
      "decimals": 4,
      "title": "AU: 0.5192 SDR = 1 AUD 2026-04-30 RBA 4.00 pm Eastern Australian time"
    }
  ]
}